jiraflow/ExampleConfig.json
jiraflow/WorkItem.py
jiraflow/WorkItemService.py
jiraflow/__init__.py
jiraflow/main.py
jiraflow-0.9.2.dist-info/LICENSE
jiraflow-0.9.2.dist-info/METADATA
jiraflow-0.9.2.dist-info/WHEEL
jiraflow-0.9.2.dist-info/entry_points.txt
jiraflow-0.9.2.dist-info/top_level.txt
jiraflow-0.9.2.dist-info/RECORD
